<?xml version="1.0" encoding="utf-8" ?><dwsync><file name="p_2048_1536_50E9C226-BC33-4961-912D-55F0D12227D3-150x150.jpg" server="whildkatz.ipower.com" local="3334892400" remote="20514761584" /><file name="p_2048_1536_50E9C226-BC33-4961-912D-55F0D12227D3-225x300.jpg" server="whildkatz.ipower.com" local="3334892400" remote="20514761584" /><file name="p_2048_1536_50E9C226-BC33-4961-912D-55F0D12227D3.jpeg" server="whildkatz.ipower.com" local="3334892400" remote="20514761584" /><file name="portfolio_th_id_elg-150x136.jpg" server="whildkatz.ipower.com" local="3344227200" remote="20524096384" /><file name="portfolio_th_id_elg.jpg" server="whildkatz.ipower.com" local="3344227200" remote="20524096384" /><file name="portfolio_th_wb_cha-150x136.jpg" server="whildkatz.ipower.com" local="3344227200" remote="20524096384" /><file name="portfolio_th_wb_cha.jpg" server="whildkatz.ipower.com" local="3344227200" remote="20524096384" /><file name="portfolio_th_wb_lpp-150x136.jpg" server="whildkatz.ipower.com" local="3344227200" remote="20524096384" /><file name="portfolio_th_wb_lpp.jpg" server="whildkatz.ipower.com" local="3344227200" remote="20524096384" /><file name="portfolio_th_wb_wk-150x136.jpg" server="whildkatz.ipower.com" local="3344227200" remote="20524096384" /><file name="portfolio_th_wb_wk.jpg" server="whildkatz.ipower.com" local="3344227200" remote="20524096384" /><file name="portfolio_web_wnk-150x150.jpg" server="whildkatz.ipower.com" local="3335670000" remote="20515539184" /><file name="portfolio_web_wnk-300x136.jpg" server="whildkatz.ipower.com" local="3335670000" remote="20515539184" /><file name="portfolio_web_wnk.jpg" server="whildkatz.ipower.com" local="3335670000" remote="20515539184" /><file name="portfolio_web_wnk2-150x150.jpg" server="whildkatz.ipower.com" local="3344227200" remote="20524096384" /><file name="portfolio_web_wnk2-300x190.jpg" server="whildkatz.ipower.com" local="3344227200" remote="20524096384" /><file name="portfolio_web_wnk2.jpg" server="whildkatz.ipower.com" local="3344227200" remote="20524096384" /><file name="p_2048_1536_50E9C226-BC33-4961-912D-55F0D12227D3-150x150.jpg" server="bkc-stage.com/Sites/BKCwp/" local="3417024916" remote="12006959612" /><file name="p_2048_1536_50E9C226-BC33-4961-912D-55F0D12227D3-225x300.jpg" server="bkc-stage.com/Sites/BKCwp/" local="3417024916" remote="12006959672" /><file name="p_2048_1536_50E9C226-BC33-4961-912D-55F0D12227D3.jpeg" server="bkc-stage.com/Sites/BKCwp/" local="3417024916" remote="12006959672" /><file name="portfolio_th_id_elg-150x136.jpg" server="bkc-stage.com/Sites/BKCwp/" local="3417024916" remote="12006959672" /><file name="portfolio_th_id_elg.jpg" server="bkc-stage.com/Sites/BKCwp/" local="3417024916" remote="12006959672" /><file name="portfolio_th_wb_cha-150x136.jpg" server="bkc-stage.com/Sites/BKCwp/" local="3417024916" remote="12006959672" /><file name="portfolio_th_wb_cha.jpg" server="bkc-stage.com/Sites/BKCwp/" local="3417024917" remote="12006959672" /><file name="portfolio_th_wb_lpp-150x136.jpg" server="bkc-stage.com/Sites/BKCwp/" local="3417024917" remote="12006959672" /><file name="portfolio_th_wb_lpp.jpg" server="bkc-stage.com/Sites/BKCwp/" local="3417024917" remote="12006959672" /><file name="portfolio_th_wb_wk-150x136.jpg" server="bkc-stage.com/Sites/BKCwp/" local="3417024917" remote="12006959672" /><file name="portfolio_th_wb_wk.jpg" server="bkc-stage.com/Sites/BKCwp/" local="3417024917" remote="12006959672" /><file name="portfolio_web_wnk-150x150.jpg" server="bkc-stage.com/Sites/BKCwp/" local="3417024917" remote="12006959672" /><file name="portfolio_web_wnk-300x136.jpg" server="bkc-stage.com/Sites/BKCwp/" local="3417024918" remote="12006959672" /><file name="portfolio_web_wnk.jpg" server="bkc-stage.com/Sites/BKCwp/" local="3417024918" remote="12006959672" /><file name="portfolio_web_wnk2-150x150.jpg" server="bkc-stage.com/Sites/BKCwp/" local="3417024918" remote="12006959672" /><file name="portfolio_web_wnk2-300x190.jpg" server="bkc-stage.com/Sites/BKCwp/" local="3417024918" remote="12006959672" /><file name="portfolio_web_wnk2.jpg" server="bkc-stage.com/Sites/BKCwp/" local="3417024918" remote="12006959672" /></dwsync>